indico_piwik/__init__.py
indico_piwik/controllers.py
indico_piwik/forms.py
indico_piwik/piwik.py
indico_piwik/plugin.py
indico_piwik/reports.py
indico_piwik/views.py
indico_piwik/queries/__init__.py
indico_piwik/queries/base.py
indico_piwik/queries/graphs.py
indico_piwik/queries/metrics.py
indico_piwik/queries/utils.py
indico_piwik/static/dist/manifest.json
indico_piwik/static/dist/css/main.0403c3b8.css
indico_piwik/static/dist/css/main.0403c3b8.css.map
indico_piwik/static/dist/js/main.9962864a.bundle.js
indico_piwik/static/dist/js/main.9962864a.bundle.js.map
indico_piwik/static/dist/js/monaco.css.worker.js
indico_piwik/static/dist/js/monaco.css.worker.js.map
indico_piwik/static/dist/js/monaco.editor.worker.js
indico_piwik/static/dist/js/monaco.editor.worker.js.map
indico_piwik/static/dist/js/monaco.html.worker.js
indico_piwik/static/dist/js/monaco.html.worker.js.map
indico_piwik/static/js/lib/jqTree/circle.png
indico_piwik/static/js/lib/jqTree/jqtree.css
indico_piwik/static/js/lib/jqTree/tree.jquery.js
indico_piwik/static/js/lib/jqTree/treeDownTriangleBlack.png
indico_piwik/static/js/lib/jqTree/treeRightTriangleBlack.png
indico_piwik/templates/statistics.html
indico_piwik/templates/tracking.html
indico_piwik/translations/messages-js.pot
indico_piwik/translations/messages.pot
indico_piwik/translations/cs_CZ/LC_MESSAGES/messages-js.po
indico_piwik/translations/cs_CZ/LC_MESSAGES/messages.mo
indico_piwik/translations/cs_CZ/LC_MESSAGES/messages.po
indico_piwik/translations/de_DE/LC_MESSAGES/messages-js.po
indico_piwik/translations/de_DE/LC_MESSAGES/messages.mo
indico_piwik/translations/de_DE/LC_MESSAGES/messages.po
indico_piwik/translations/en_CA/LC_MESSAGES/messages-js.po
indico_piwik/translations/en_CA/LC_MESSAGES/messages.mo
indico_piwik/translations/en_CA/LC_MESSAGES/messages.po
indico_piwik/translations/en_GB/LC_MESSAGES/messages-js.po
indico_piwik/translations/en_GB/LC_MESSAGES/messages.mo
indico_piwik/translations/en_GB/LC_MESSAGES/messages.po
indico_plugin_piwik-3.3.3.dist-info/METADATA
indico_plugin_piwik-3.3.3.dist-info/WHEEL
indico_plugin_piwik-3.3.3.dist-info/entry_points.txt
indico_plugin_piwik-3.3.3.dist-info/RECORD
